citecheck/__init__.py
citecheck/_version.py
citecheck/core/__init__.py
citecheck/core/cite.py
citecheck/core/citeas.py
citecheck/core/cited.py
citecheck/core/citedmixin.py
citecheck/core/errors.py
citecheck/core/uncite.py
citecheck/core/types/__init__.py
citecheck/core/types/citable.py
citecheck/core/types/citation.py
citecheck/decorate/__init__.py
citecheck/decorate/citedinput.py
citecheck/decorate/citedreturn.py
citecheck/decorate/enforcecite.py
citecheck-0.3.0.dist-info/LICENSE.txt
citecheck-0.3.0.dist-info/METADATA
citecheck-0.3.0.dist-info/WHEEL
citecheck-0.3.0.dist-info/top_level.txt
citecheck-0.3.0.dist-info/RECORD
