Metadata-Version: 2.1
Name: citecheck
Version: 0.3.0
Summary: Run-time protection of citation chains
Author-email: Nathan McDougall <nathan.j.mcdougall@gmail.com>
License: BSD-3-Clause
Project-URL: Docs: User Guide, https://citecheck.readthedocs.io/en/latest/
Project-URL: Source Code, https://github.com/nathanjmcdougall/citecheck
Project-URL: homepage, https://github.com/nathanjmcdougall/citecheck
Project-URL: What's New, https://citecheck.readthedocs.io/en/latest/whatsnew/releasenotes.html
Project-URL: Bug Tracker, https://github.com/nathanjmcdougall/citecheck/issues
Keywords: citations,cite,bibliography,annotations,references,bibtex,research,academic,methodology,equations
Classifier: Development Status :: 2 - Pre-Alpha
Classifier: Intended Audience :: Developers
Classifier: Intended Audience :: Science/Research
Classifier: Intended Audience :: Information Technology
Classifier: License :: OSI Approved :: BSD License
Classifier: Operating System :: OS Independent
Classifier: Programming Language :: Python
Classifier: Programming Language :: Python :: 3
Classifier: Programming Language :: Python :: 3 :: Only
Classifier: Programming Language :: Python :: 3.8
Classifier: Programming Language :: Python :: 3.9
Classifier: Programming Language :: Python :: 3.10
Classifier: Programming Language :: Python :: 3.11
Classifier: Topic :: Scientific/Engineering
Classifier: Topic :: Software Development :: Documentation
Classifier: Topic :: Software Development :: Testing
Classifier: Topic :: Documentation
Classifier: Typing :: Typed
Requires-Python: >=3.8
License-File: LICENSE.txt
Provides-Extra: check
Requires-Dist: pre-commit ; extra == 'check'
Requires-Dist: mypy (==1.2.0) ; extra == 'check'
Provides-Extra: dev
Requires-Dist: pip-tools ; extra == 'dev'
Requires-Dist: setuptools-scm[toml] ; extra == 'dev'
Requires-Dist: black (==23.3.0) ; extra == 'dev'
Requires-Dist: pylint (==3.0.0a6) ; extra == 'dev'
Requires-Dist: ruff (==0.0.263) ; extra == 'dev'
Provides-Extra: doc
Requires-Dist: tomli ; extra == 'doc'
Requires-Dist: towncrier ; extra == 'doc'
Requires-Dist: sphinx ; extra == 'doc'
Requires-Dist: pydata-sphinx-theme ; extra == 'doc'
Requires-Dist: sphinx-copybutton ; extra == 'doc'
Requires-Dist: sphinx-design ; extra == 'doc'
Requires-Dist: sphinx-toggleprompt ; extra == 'doc'
Requires-Dist: sphinx-favicon ; extra == 'doc'
Provides-Extra: notebook
Requires-Dist: ipykernel ; extra == 'notebook'
Requires-Dist: IPython ; extra == 'notebook'
Provides-Extra: test
Requires-Dist: pytest ; extra == 'test'
Requires-Dist: coverage[toml] ; extra == 'test'
Requires-Dist: pytest-cov ; extra == 'test'
